{
  "H_tx": "228450230706053962261311333787903445758429166434840036167430340101278354802",
  "H_str": "34382029699540873122803447126504417751075573879883952527681761586740053945043",
  "calldata": [
    "87",
    "58",
    "222",
    "129",
    "0",
    "0",
    "0",
    "0",
    "0",
    "0",
    "0",
    "0",
    "0",
    "0",
    "0",
    "0",
    "218",
    "193",
    "127",
    "149",
    "141",
    "46",
    "229",
    "35",
    "162",
    "32",
    "98",
    "6",
    "153",
    "69",
    "151",
    "193",
    "61",
    "131",
    "30",
    "199",
    "0",
    "0",
    "0",
    "0",
    "0",
    "0",
    "0",
    "0",
    "0",
    "0",
    "0",
    "0",
    "0",
    "0",
    "0",
    "0",
    "0",
    "0",
    "0",
    "0",
    "0",
    "0",
    "0",
    "0",
    "0",
    "0",
    "0",
    "0",
    "29",
    "205",
    "101",
    "0",
    "0",
    "0",
    "0",
    "0",
    "0",
    "0",
    "0",
    "0",
    "0",
    "0",
    "0",
    "0",
    "0",
    "0",
    "0",
    "0",
    "0",
    "0",
    "0",
    "0",
    "0",
    "0",
    "0",
    "0",
    "0",
    "0",
    "0",
    "0",
    "0",
    "0",
    "0",
    "1",
    "0",
    "0",
    "0",
    "0",
    "0",
    "0",
    "0",
    "0",
    "0",
    "0",
    "0",
    "0",
    "116",
    "45",
    "53",
    "204",
    "102",
    "52",
    "192",
    "83",
    "41",
    "37",
    "163",
    "184",
    "68",
    "188",
    "69",
    "78",
    "68",
    "56",
    "244",
    "78",
    "0",
    "0",
    "0",
    "0",
    "0",
    "0",
    "0",
    "0",
    "0",
    "0",
    "0",
    "0",
    "0",
    "0",
    "0",
    "0",
    "0",
    "0",
    "0",
    "0",
    "0",
    "0",
    "0",
    "0",
    "0",
    "0",
    "0",
    "0",
    "0",
    "0",
    "0",
    "0"
  ],
  "calldata_len": "132",
  "action_type": "2",
  "token_idx": "1",
  "int_digits": [
    "0",
    "0",
    "0",
    "0",
    "0",
    "0",
    "0",
    "5",
    "0",
    "0"
  ],
  "frac_digits": [
    "0",
    "0",
    "0",
    "0",
    "0",
    "0",
    "0",
    "0",
    "0",
    "0",
    "0",
    "0",
    "0",
    "0",
    "0",
    "0",
    "0",
    "0"
  ],
  "n_leading_zeros": "7",
  "rate_mode": "1",
  "human_string": [
    "82",
    "101",
    "112",
    "97",
    "121",
    "32",
    "48",
    "48",
    "48",
    "48",
    "48",
    "48",
    "48",
    "53",
    "48",
    "48",
    "46",
    "48",
    "48",
    "48",
    "48",
    "48",
    "48",
    "48",
    "48",
    "48",
    "48",
    "48",
    "48",
    "48",
    "48",
    "48",
    "48",
    "48",
    "48",
    "32",
    "85",
    "83",
    "68",
    "84",
    "0",
    "0",
    "32",
    "40",
    "115",
    "116",
    "97",
    "98",
    "108",
    "101",
    "41",
    "0",
    "0",
    "0",
    "0",
    "0",
    "0",
    "0",
    "0",
    "0",
    "0",
    "0",
    "0",
    "0"
  ]
}